{
  "config": {
    "src": "quizmo",
    "interactiveTitle": "",
    "css": ["interactives/05_02_05_drop/styles.css"],
    "progressBar": true,
    "resultsPage": false,
    "_slidesToDisplay": 4,
    "disableRemoteCss": true,

    "modal": {
      "directions": "For each pull-down menu, select the correct word to form a complete sentence.",
      "title": "Instructions"
    }
  },
  "body": [
    [
      {
        "type": "text",
        "content": "My older sister’s bedroom has a bed."
      },
      {
        "type": "fitb",
        "quiz": "*_*_*_*_*_ <span lang='zh-Hans'>。</span>",
        "options": [
          {
            "answer": "<span lang='zh-Hans'>我姐姐</span>",
            "options": [
              "<span lang='zh-Hans'>卧室</span>", 
              "<span lang='zh-Hans'>的</span>",
              "<span lang='zh-Hans'>她</span>",
              "<span lang='zh-Hans'>他</span>",
              "<span lang='zh-Hans'>我妈妈</span>",
              "<span lang='zh-Hans'>要</span>",
              "<span lang='zh-Hans'>星期一</span>",
              "<span lang='zh-Hans'>整理</span>",
              "<span lang='zh-Hans'>有</span>",
              "<span lang='zh-Hans'>床头柜</span>",
              "<span lang='zh-Hans'>阳台</span>",
              "<span lang='zh-Hans'>床</span>"
            ]
          },
          {
            "answer": "<span lang='zh-Hans'>的</span>",
            "options": [
              "<span lang='zh-Hans'>我姐姐</span>",
              "<span lang='zh-Hans'>卧室</span>",
              "<span lang='zh-Hans'>她</span>",
              "<span lang='zh-Hans'>他</span>",
              "<span lang='zh-Hans'>我妈妈</span>",
              "<span lang='zh-Hans'>要</span>",
              "<span lang='zh-Hans'>星期一</span>",
              "<span lang='zh-Hans'>整理</span>",
              "<span lang='zh-Hans'>有</span>",
              "<span lang='zh-Hans'>床头柜</span>",
              "<span lang='zh-Hans'>阳台</span>",
              "<span lang='zh-Hans'>床</span>"
            ]
          },
          {
            "answer": "<span lang='zh-Hans'>卧室</span>",
            "options": [
              "<span lang='zh-Hans'>我姐姐</span>",
              "<span lang='zh-Hans'>的</span>",
              "<span lang='zh-Hans'>她</span>",
              "<span lang='zh-Hans'>他</span>",
              "<span lang='zh-Hans'>我妈妈</span>",
              "<span lang='zh-Hans'>要</span>",
              "<span lang='zh-Hans'>星期一</span>",
              "<span lang='zh-Hans'>整理</span>",
              "<span lang='zh-Hans'>有</span>",
              "<span lang='zh-Hans'>床头柜</span>",
              "<span lang='zh-Hans'>阳台</span>",
              "<span lang='zh-Hans'>床</span>"
            ]
          },
          {
            "answer": "<span lang='zh-Hans'>有</span>",
            "options": [
              "<span lang='zh-Hans'>我姐姐</span>",
              "<span lang='zh-Hans'>卧室</span>", 
              "<span lang='zh-Hans'>的</span>",
              "<span lang='zh-Hans'>她</span>",
              "<span lang='zh-Hans'>他</span>",
              "<span lang='zh-Hans'>我妈妈</span>",
              "<span lang='zh-Hans'>要</span>",
              "<span lang='zh-Hans'>星期一</span>",
              "<span lang='zh-Hans'>整理</span>",
              "<span lang='zh-Hans'>床头柜</span>",
              "<span lang='zh-Hans'>阳台</span>",
              "<span lang='zh-Hans'>床</span>"
            ]
          },
          {
            "answer": "<span lang='zh-Hans'>床</span>",
            "options": [
              "<span lang='zh-Hans'>我姐姐</span>",
              "<span lang='zh-Hans'>卧室</span>", 
              "<span lang='zh-Hans'>的</span>",
              "<span lang='zh-Hans'>她</span>",
              "<span lang='zh-Hans'>他</span>",
              "<span lang='zh-Hans'>我妈妈</span>",
              "<span lang='zh-Hans'>要</span>",
              "<span lang='zh-Hans'>星期一</span>",
              "<span lang='zh-Hans'>整理</span>",
              "<span lang='zh-Hans'>有</span>",
              "<span lang='zh-Hans'>床头柜</span>",
              "<span lang='zh-Hans'>阳台</span>"
            ]
          }
        ],
        "chances": 2,
        "correctHeading": "Correct",
        "correct": "You got it! <span lang='zh-Hans'>我姐姐的卧室有床。</span> means “My older sister’s bedroom has a bed.”",
        "incorrect": "Not quite. Please try again!",
        "incorrectHeading": "Incorrect",
        "failedHeading": "Incorrect",
        "failed": "You've tried too many times. The correct answer has been filled in for you."
      }
    ],
    [
      {
        "type": "text",
        "content": "Her bedroom has a nightstand."
      },
      {
        "type": "fitb",
        "quiz": "*_*_*_*_*_ <span lang='zh-Hans'>。</span>",
        "options": [
          {
            "answer": "<span lang='zh-Hans'>她</span>",
            "options": [
              "<span lang='zh-Hans'>我姐姐</span>",
              "<span lang='zh-Hans'>卧室</span>", 
              "<span lang='zh-Hans'>的</span>",
              "<span lang='zh-Hans'>他</span>",
              "<span lang='zh-Hans'>我妈妈</span>",
              "<span lang='zh-Hans'>要</span>",
              "<span lang='zh-Hans'>星期一</span>",
              "<span lang='zh-Hans'>整理</span>",
              "<span lang='zh-Hans'>有</span>",
              "<span lang='zh-Hans'>床头柜</span>",
              "<span lang='zh-Hans'>阳台</span>",
              "<span lang='zh-Hans'>床</span>"
            ]
          },
          {
            "answer": "<span lang='zh-Hans'>的</span>",
            "options": [
              "<span lang='zh-Hans'>我姐姐</span>",
              "<span lang='zh-Hans'>卧室</span>",
              "<span lang='zh-Hans'>她</span>",
              "<span lang='zh-Hans'>他</span>",
              "<span lang='zh-Hans'>我妈妈</span>",
              "<span lang='zh-Hans'>要</span>",
              "<span lang='zh-Hans'>星期一</span>",
              "<span lang='zh-Hans'>整理</span>",
              "<span lang='zh-Hans'>有</span>",
              "<span lang='zh-Hans'>床头柜</span>",
              "<span lang='zh-Hans'>阳台</span>",
              "<span lang='zh-Hans'>床</span>"
            ]
          },
          {
            "answer": "<span lang='zh-Hans'>卧室</span>",
            "options": [
              "<span lang='zh-Hans'>我姐姐</span>", 
              "<span lang='zh-Hans'>的</span>",
              "<span lang='zh-Hans'>她</span>",
              "<span lang='zh-Hans'>他</span>",
              "<span lang='zh-Hans'>我妈妈</span>",
              "<span lang='zh-Hans'>要</span>",
              "<span lang='zh-Hans'>星期一</span>",
              "<span lang='zh-Hans'>整理</span>",
              "<span lang='zh-Hans'>有</span>",
              "<span lang='zh-Hans'>床头柜</span>",
              "<span lang='zh-Hans'>阳台</span>",
              "<span lang='zh-Hans'>床</span>"
            ]
          },
          {
            "answer": "<span lang='zh-Hans'>有</span>",
            "options": [
              "<span lang='zh-Hans'>我姐姐</span>",
              "<span lang='zh-Hans'>卧室</span>", 
              "<span lang='zh-Hans'>的</span>",
              "<span lang='zh-Hans'>她</span>",
              "<span lang='zh-Hans'>他</span>",
              "<span lang='zh-Hans'>我妈妈</span>",
              "<span lang='zh-Hans'>要</span>",
              "<span lang='zh-Hans'>星期一</span>",
              "<span lang='zh-Hans'>整理</span>",
              "<span lang='zh-Hans'>床头柜</span>",
              "<span lang='zh-Hans'>阳台</span>",
              "<span lang='zh-Hans'>床</span>"
            ]
          },
          {
            "answer": "<span lang='zh-Hans'>床头柜</span>",
            "options": [
              "<span lang='zh-Hans'>我姐姐</span>",
              "<span lang='zh-Hans'>卧室</span>", 
              "<span lang='zh-Hans'>的</span>",
              "<span lang='zh-Hans'>她</span>",
              "<span lang='zh-Hans'>他</span>",
              "<span lang='zh-Hans'>我妈妈</span>",
              "<span lang='zh-Hans'>要</span>",
              "<span lang='zh-Hans'>星期一</span>",
              "<span lang='zh-Hans'>整理</span>",
              "<span lang='zh-Hans'>有</span>",
              "<span lang='zh-Hans'>阳台</span>",
              "<span lang='zh-Hans'>床</span>"
            ]
          }
        ],
        "chances": 2,
        "correctHeading": "Correct",
        "correct": "You got it! <span lang='zh-Hans'>她的卧室有床头柜。</span>. means “Her bedroom has a nightstand.”",
        "incorrect": "Not quite. Please try again!",
        "incorrectHeading": "Incorrect",
        "failedHeading": "Incorrect",
        "failed": "You've tried too many times. The correct answer has been filled in for you."
      }
    ],
    [
      {
        "type": "text",
        "content": "He is going to tidy up the bedroom."
      },
      {
        "type": "fitb",
        "quiz": "*_*_*_*_ <span lang='zh-Hans'>。</span>",
        "options": [
          {
            "answer": "<span lang='zh-Hans'>他</span>",
            "options": [             
              "<span lang='zh-Hans'>我姐姐</span>",
              "<span lang='zh-Hans'>卧室</span>", 
              "<span lang='zh-Hans'>的</span>",
              "<span lang='zh-Hans'>她</span>",
              "<span lang='zh-Hans'>我妈妈</span>",
              "<span lang='zh-Hans'>要</span>",
              "<span lang='zh-Hans'>星期一</span>",
              "<span lang='zh-Hans'>整理</span>",
              "<span lang='zh-Hans'>有</span>",
              "<span lang='zh-Hans'>床头柜</span>",
              "<span lang='zh-Hans'>阳台</span>",
              "<span lang='zh-Hans'>床</span>"
            ]
          },
          {
            "answer": "<span lang='zh-Hans'>要</span>",
            "options": [
              "<span lang='zh-Hans'>我姐姐</span>",
              "<span lang='zh-Hans'>卧室</span>", 
              "<span lang='zh-Hans'>的</span>",
              "<span lang='zh-Hans'>她</span>",
              "<span lang='zh-Hans'>他</span>",
              "<span lang='zh-Hans'>我妈妈</span>",
              "<span lang='zh-Hans'>星期一</span>",
              "<span lang='zh-Hans'>整理</span>",
              "<span lang='zh-Hans'>有</span>",
              "<span lang='zh-Hans'>床头柜</span>",
              "<span lang='zh-Hans'>阳台</span>",
              "<span lang='zh-Hans'>床</span>"
            ]
          },
          {
            "answer": "<span lang='zh-Hans'>整理</span>",
            "options": [
              "<span lang='zh-Hans'>我姐姐</span>",
              "<span lang='zh-Hans'>卧室</span>", 
              "<span lang='zh-Hans'>的</span>",
              "<span lang='zh-Hans'>她</span>",
              "<span lang='zh-Hans'>他</span>",
              "<span lang='zh-Hans'>我妈妈</span>",
              "<span lang='zh-Hans'>要</span>",
              "<span lang='zh-Hans'>星期一</span>",
              "<span lang='zh-Hans'>有</span>",
              "<span lang='zh-Hans'>床头柜</span>",
              "<span lang='zh-Hans'>阳台</span>",
              "<span lang='zh-Hans'>床</span>"
            ]
          },
          {
            "answer": "<span lang='zh-Hans'>卧室</span>",
            "options": [
              "<span lang='zh-Hans'>我姐姐</span>", 
              "<span lang='zh-Hans'>的</span>",
              "<span lang='zh-Hans'>她</span>",
              "<span lang='zh-Hans'>他</span>",
              "<span lang='zh-Hans'>我妈妈</span>",
              "<span lang='zh-Hans'>要</span>",
              "<span lang='zh-Hans'>星期一</span>",
              "<span lang='zh-Hans'>整理</span>",
              "<span lang='zh-Hans'>有</span>",
              "<span lang='zh-Hans'>床头柜</span>",
              "<span lang='zh-Hans'>阳台</span>",
              "<span lang='zh-Hans'>床</span>"
            ]
          }
        ],
        "chances": 2,
        "correctHeading": "Correct",
        "correct": "You got it! <span lang='zh-Hans'>他要整理卧室。</span>. means “He is going to tidy up the bedroom.”",
        "incorrect": "Not quite. Please try again!",
        "incorrectHeading": "Incorrect",
        "failedHeading": "Incorrect",
        "failed": "You've tried too many times. The correct answer has been filled in for you."
      }
    ],
    [
      {
        "type": "text",
        "content": "My mom is going to tidy up the balcony on Monday."
      },
      {
        "type": "fitb",
        "quiz": "*_*_*_*_*_ <span lang='zh-Hans'>。</span>",
        "options": [
          {
            "answer": "<span lang='zh-Hans'>我妈妈</span>",
            "options": [
              "<span lang='zh-Hans'>我姐姐</span>",
              "<span lang='zh-Hans'>卧室</span>", 
              "<span lang='zh-Hans'>的</span>",
              "<span lang='zh-Hans'>她</span>",
              "<span lang='zh-Hans'>他</span>",
              "<span lang='zh-Hans'>要</span>",
              "<span lang='zh-Hans'>星期一</span>",
              "<span lang='zh-Hans'>整理</span>",
              "<span lang='zh-Hans'>有</span>",
              "<span lang='zh-Hans'>床头柜</span>",
              "<span lang='zh-Hans'>阳台</span>",
              "<span lang='zh-Hans'>床</span>"
            ]
          },
          {
            "answer": "<span lang='zh-Hans'>星期一</span>",
            "options": [
              "<span lang='zh-Hans'>我姐姐</span>",
              "<span lang='zh-Hans'>卧室</span>", 
              "<span lang='zh-Hans'>的</span>",
              "<span lang='zh-Hans'>她</span>",
              "<span lang='zh-Hans'>他</span>",
              "<span lang='zh-Hans'>我妈妈</span>",
              "<span lang='zh-Hans'>要</span>",
              "<span lang='zh-Hans'>整理</span>",
              "<span lang='zh-Hans'>有</span>",
              "<span lang='zh-Hans'>床头柜</span>",
              "<span lang='zh-Hans'>阳台</span>",
              "<span lang='zh-Hans'>床</span>"
            ]
          },
          {
            "answer": "<span lang='zh-Hans'>要</span>",
            "options": [
              "<span lang='zh-Hans'>我姐姐</span>",
              "<span lang='zh-Hans'>卧室</span>", 
              "<span lang='zh-Hans'>的</span>",
              "<span lang='zh-Hans'>她</span>",
              "<span lang='zh-Hans'>他</span>",
              "<span lang='zh-Hans'>我妈妈</span>",
              "<span lang='zh-Hans'>星期一</span>",
              "<span lang='zh-Hans'>整理</span>",
              "<span lang='zh-Hans'>有</span>",
              "<span lang='zh-Hans'>床头柜</span>",
              "<span lang='zh-Hans'>阳台</span>",
              "<span lang='zh-Hans'>床</span>"
            ]
          },
          {
            "answer": "<span lang='zh-Hans'>整理</span>",
            "options": [
              "<span lang='zh-Hans'>我姐姐</span>",
              "<span lang='zh-Hans'>卧室</span>", 
              "<span lang='zh-Hans'>的</span>",
              "<span lang='zh-Hans'>她</span>",
              "<span lang='zh-Hans'>他</span>",
              "<span lang='zh-Hans'>我妈妈</span>",
              "<span lang='zh-Hans'>要</span>",
              "<span lang='zh-Hans'>星期一</span>",
              "<span lang='zh-Hans'>有</span>",
              "<span lang='zh-Hans'>床头柜</span>",
              "<span lang='zh-Hans'>阳台</span>",
              "<span lang='zh-Hans'>床</span>"
            ]
          },
          {
            "answer": "<span lang='zh-Hans'>阳台</span>",
            "options": [
              "<span lang='zh-Hans'>我姐姐</span>",
              "<span lang='zh-Hans'>卧室</span>", 
              "<span lang='zh-Hans'>的</span>",
              "<span lang='zh-Hans'>她</span>",
              "<span lang='zh-Hans'>他</span>",
              "<span lang='zh-Hans'>我妈妈</span>",
              "<span lang='zh-Hans'>要</span>",
              "<span lang='zh-Hans'>星期一</span>",
              "<span lang='zh-Hans'>整理</span>",
              "<span lang='zh-Hans'>有</span>",
              "<span lang='zh-Hans'>床头柜</span>",
              "<span lang='zh-Hans'>床</span>"
            ]
          }
        ],
        "chances": 2,
        "correctHeading": "Correct",
        "correct": "You got it! <span lang='zh-Hans'>我妈妈星期一要整理阳台。</span>. means “My mom is going to tidy up the balcony on Monday.”",
        "incorrect": "Not quite. Please try again!",
        "incorrectHeading": "Incorrect",
        "failedHeading": "Incorrect",
        "failed": "You've tried too many times. The correct answer has been filled in for you."
      }
    ]
  ]
}


